blind_ai/__init__.py
blind_ai/cli.py
blind_ai/py.typed
blind_ai/api/__init__.py
blind_ai/api/app.py
blind_ai/api/auth.py
blind_ai/api/models.py
blind_ai/api/routes/__init__.py
blind_ai/api/routes/protect.py
blind_ai/api/routes/signup.py
blind_ai/api/routes/tools.py
blind_ai/core/__init__.py
blind_ai/core/models.py
blind_ai/core/orchestrator.py
blind_ai/core/chains/__init__.py
blind_ai/core/chains/models.py
blind_ai/core/chains/tracker.py
blind_ai/core/detection/__init__.py
blind_ai/core/detection/enhanced_detector.py
blind_ai/core/detection/enhanced_matcher.py
blind_ai/core/detection/static.py
blind_ai/core/detection/ml/__init__.py
blind_ai/core/detection/ml/cache.py
blind_ai/core/detection/ml/context.py
blind_ai/core/detection/ml/detector.py
blind_ai/core/detection/ml/heuristics.py
blind_ai/core/detection/ml/preprocessing.py
blind_ai/core/detection/patterns/__init__.py
blind_ai/core/detection/patterns/pii.py
blind_ai/core/detection/patterns/prompt.py
blind_ai/core/detection/patterns/sql.py
blind_ai/core/detection/patterns/validation_mapping.py
blind_ai/core/detection/patterns/validators.py
blind_ai/core/policy/parser.py
blind_ai/core/policy/policy.py
blind_ai/core/ratelimit/__init__.py
blind_ai/core/ratelimit/limiter.py
blind_ai/core/rbac/__init__.py
blind_ai/core/rbac/authorizer.py
blind_ai/core/rbac/models.py
blind_ai/core/registry/__init__.py
blind_ai/core/registry/metadata.py
blind_ai/core/registry/storage.py
blind_ai/core/validation/__init__.py
blind_ai/core/validation/models.py
blind_ai/core/validation/validator.py
blind_ai/integrations/__init__.py
blind_ai/integrations/autogen.py
blind_ai/integrations/crewai.py
blind_ai/integrations/haystack.py
blind_ai/integrations/langchain.py
blind_ai/integrations/llamaindex.py
blind_ai/integrations/observability.py
blind_ai/integrations/registry.py
blind_ai/integrations/semantic_kernel.py
blind_ai/integrations/utils.py
blind_ai/sdk/__init__.py
blind_ai/sdk/async_client.py
blind_ai/sdk/circuit_breaker.py
blindai_guard-0.1.0.dist-info/licenses/LICENSE
blindai_guard-0.1.0.dist-info/METADATA
blindai_guard-0.1.0.dist-info/WHEEL
blindai_guard-0.1.0.dist-info/entry_points.txt
blindai_guard-0.1.0.dist-info/top_level.txt
blindai_guard-0.1.0.dist-info/RECORD
