Metadata-Version: 2.4
Name: blindai-guard
Version: 0.1.0
Summary: Runtime security for AI agents - prevent prompt injection and data exfiltration
Author-email: Blind AI Team <team@blindai.dev>
License: Apache-2.0
Project-URL: Homepage, https://blind-ai.vercel.app
Project-URL: Documentation, https://github.com/logicshaper19/blindAI#readme
Project-URL: Repository, https://github.com/logicshaper19/blindAI
Project-URL: Issues, https://github.com/logicshaper19/blindAI/issues
Keywords: ai,security,llm,prompt-injection,data-loss-prevention
Classifier: Development Status :: 3 - Alpha
Classifier: Intended Audience :: Developers
Classifier: License :: OSI Approved :: Apache Software License
Classifier: Programming Language :: Python :: 3
Classifier: Programming Language :: Python :: 3.11
Classifier: Programming Language :: Python :: 3.12
Classifier: Topic :: Security
Classifier: Topic :: Software Development :: Libraries :: Python Modules
Requires-Python: >=3.11
License-File: LICENSE
Requires-Dist: pyahocorasick>=2.0.0
Requires-Dist: fastapi>=0.104.0
Requires-Dist: uvicorn[standard]>=0.24.0
Requires-Dist: pydantic[email]>=2.5.0
Requires-Dist: onnxruntime>=1.16.0
Requires-Dist: transformers>=4.35.0
Requires-Dist: redis>=5.0.0
Requires-Dist: clickhouse-driver>=0.2.6
Requires-Dist: pyyaml>=6.0.1
Requires-Dist: python-multipart>=0.0.6
Requires-Dist: httpx>=0.25.0
Provides-Extra: dev
Requires-Dist: pytest>=7.4.3; extra == "dev"
Requires-Dist: pytest-cov>=4.1.0; extra == "dev"
Requires-Dist: pytest-asyncio>=0.21.0; extra == "dev"
Requires-Dist: pytest-mock>=3.12.0; extra == "dev"
Requires-Dist: mypy>=1.7.0; extra == "dev"
Requires-Dist: ruff>=0.1.6; extra == "dev"
Requires-Dist: black>=23.11.0; extra == "dev"
Requires-Dist: isort>=5.12.0; extra == "dev"
Requires-Dist: radon>=6.0.1; extra == "dev"
Requires-Dist: locust>=2.18.0; extra == "dev"
Requires-Dist: memory-profiler>=0.61.0; extra == "dev"
Dynamic: license-file
